README.rst
setup.cfg
setup.py
pymycity/__init__.py
pymycity/__main__.py
pymycity/item.py
pymycity/misc.py
pymycity.egg-info/PKG-INFO
pymycity.egg-info/SOURCES.txt
pymycity.egg-info/dependency_links.txt
pymycity.egg-info/entry_points.txt
pymycity.egg-info/requires.txt
pymycity.egg-info/top_level.txt
pymycity/cities/__init__.py
pymycity/cities/mascouche/__init__.py
pymycity/cities/mascouche/events.py
pymycity/cities/mascouche/garbage_collection.py
pymycity/cities/mascouche/taxes.py
pymycity/cities/montreal/__init__.py
pymycity/cities/montreal/taxes.py