Metadata-Version: 1.1
Name: pymycity
Version: 0.2.5
Summary: Get your city live information
Home-page: http://github.com/titilambert/pymycity
Author: Thibault Cohen
Author-email: titilambert@gmail.com
License: UNKNOWN
Platform: UNKNOWN
Classifier: Programming Language :: Python :: 3.4
Classifier: Programming Language :: Python :: 3.5
Classifier: Programming Language :: Python :: 3.6
